galaxy_jukebox_gui/__init__.py
galaxy_jukebox_gui/__main__.py
galaxy_jukebox_gui/gui.py
galaxy_jukebox_gui/gui_icons/0side_lamp.png
galaxy_jukebox_gui/gui_icons/0side_nolamp.png
galaxy_jukebox_gui/gui_icons/1side_lamp.png
galaxy_jukebox_gui/gui_icons/1side_nolamp.png
galaxy_jukebox_gui/gui_icons/2side_lamp.png
galaxy_jukebox_gui/gui_icons/2side_nolamp.png
galaxy_jukebox_gui/gui_icons/3side_lamp.png
galaxy_jukebox_gui/gui_icons/3side_nolamp.png
galaxy_jukebox_gui-1.0.0.dist-info/entry_points.txt
galaxy_jukebox_gui-1.0.0.dist-info/LICENSE
galaxy_jukebox_gui-1.0.0.dist-info/WHEEL
galaxy_jukebox_gui-1.0.0.dist-info/METADATA
galaxy_jukebox_gui-1.0.0.dist-info/RECORD
