Metadata-Version: 2.1
Name: galaxy-jukebox-gui
Version: 1.0.0
Summary: Graphical user interface for Galaxy Jukebox, which is a schematic exporter for Minecraft Note Block Studio.
Keywords: minecraft,note,block,noteblock,schematic,redstone
Author-email: 1234ab <nevenincs007@gmail.com>
Classifier: License :: OSI Approved :: GNU General Public License v3 or later (GPLv3+)
Classifier: Programming Language :: Python :: 3
Requires-Dist: PyQt5 >=5.15.0
Requires-Dist: galaxy-jukebox >=1.0.0
Project-URL: Home, https://github.com/4321ba/Galaxy_Jukebox
